README.rst
setup.py
nlcalc/__init__.py
nlcalc/calculator.py
nlcalc/context.py
nlcalc/operations.py
nlcalc/utils.py
nlcalc.egg-info/PKG-INFO
nlcalc.egg-info/SOURCES.txt
nlcalc.egg-info/dependency_links.txt
nlcalc.egg-info/requires.txt
nlcalc.egg-info/top_level.txt