Metadata-Version: 1.1
Name: nlcalc
Version: 0.1.1
Summary: Natural Language Mathematical Calculator
Home-page: https://github.com/pri22296/nlcalc
Author: Priyam Singh
Author-email: priyamsingh.22296@gmail.com
License: MIT
Download-URL: https://github.com/pri22296/nlcalc/tarball/0.1.1
Platform: UNKNOWN
Classifier: Development Status :: 3 - Alpha
Classifier: Intended Audience :: Developers
Classifier: License :: OSI Approved :: MIT License
Classifier: Programming Language :: Python
Classifier: Programming Language :: Python :: 3.5
